[
    {
      "product_id": "P001",
      "product_title": "Samsung Galaxy Z Fold 4",
      "product_image": "https://i.ibb.co.com/h7t81xK/Samsung-Galaxy-Z-Fold-4-1.jpg",
      "category": "Iphone",
      "price": 1799,
      "description": "Samsung Galaxy Z Fold 4 with foldable 7.6-inch display, 5G, and 12GB RAM.",
      "Specification": ["7.6-inch Foldable Display", "12GB RAM", "4400mAh Battery", "5G Connectivity"],
      "availability": true,
      "rating": 4.7
    },
    {
      "product_id": "P002",
      "product_title": "iPhone 14 Pro Max",
      "product_image": "https://i.ibb.co.com/TWBnjfH/i-Phone-14-Pro-Max-2.jpg",
      "category": "Iphone",
      "price": 1199,
      "description": "Apple iPhone 14 Pro Max with A16 Bionic chip, ProMotion 120Hz display, and advanced camera system.",
      "Specification": ["A16 Bionic", "120Hz Display", "48MP Main Camera", "4323mAh Battery"],
      "availability": true,
      "rating": 4.9
    },
    {
      "product_id": "P003",
      "product_title": "Google Pixel 7",
      "product_image": "https://i.ibb.co.com/RQ0HCwj/Google-Pixel-7-3.jpg",
      "category": "Iphone",
      "price": 649,
      "description": "Google Pixel 7 with Google Tensor G2 chip, high-quality 50MP dual camera, and long-lasting battery.",
      "Specification": ["Google Tensor G2", "50MP Dual Camera", "4355mAh Battery", "IP68 Water Resistance"],
      "availability": true,
      "rating": 4.6
    },
    {
      "product_id": "P004",
      "product_title": "OnePlus 10 Pro",
      "product_image": "https://i.ibb.co.com/Rp6HFjm/One-Plus-10-Pro-4.jpg",
      "category": "Smartphones",
      "price": 899,
      "description": "OnePlus 10 Pro with Snapdragon 8 Gen 1, Fluid AMOLED display, and Hasselblad camera.",
      "Specification": ["Snapdragon 8 Gen 1", "120Hz AMOLED", "5000mAh Battery", "80W Fast Charging"],
      "availability": true,
      "rating": 4.5
    },
    {
      "product_id": "P005",
      "product_title": "Sony Xperia 5 IV",
      "product_image": "https://i.ibb.co.com/YbYyv9M/Sony-Xperia-5-IV-5.jpg",
      "category": "Smartphones",
      "price": 999,
      "description": "Sony Xperia 5 IV with 120Hz OLED display, 12MP triple camera, and high-resolution audio support.",
      "Specification": ["120Hz OLED", "12MP Triple Camera", "5000mAh Battery", "High-Res Audio"],
      "availability": false,
      "rating": 4.4
    },
    {
      "product_id": "P006",
      "product_title": "Xiaomi 12 Pro",
      "product_image": "https://i.ibb.co.com/G5CZSxQ/Xiaomi-12-Pro-6.jpg",
      "category": "Smartphones",
      "price": 849,
      "description": "Xiaomi 12 Pro with Snapdragon 8 Gen 1, 120W fast charging, and 50MP triple camera setup.",
      "Specification": ["Snapdragon 8 Gen 1", "50MP Triple Camera", "4600mAh Battery", "120W Fast Charging"],
      "availability": true,
      "rating": 4.6
    },
    {
      "product_id": "P007",
      "product_title": "Motorola Edge 30 Ultra",
      "product_image": "https://i.ibb.co.com/F4Khxcs/Motorola-Edge-30-Ultra-7.jpg",
      "category": "Smartphones",
      "price": 799,
      "description": "Motorola Edge 30 Ultra with Snapdragon 8+ Gen 1, 144Hz OLED display, and 200MP main camera.",
      "Specification": ["Snapdragon 8+ Gen 1", "144Hz OLED", "200MP Camera", "125W Fast Charging"],
      "availability": true,
      "rating": 4.7
    },
    {
      "product_id": "P008",
      "product_title": "Vivo X80 Pro",
      "product_image": "https://i.ibb.co.com/Rp00K9r/Vivo-X80-Pro-8.jpg",
      "category": "Smartphones",
      "price": 899,
      "description": "Vivo X80 Pro with Snapdragon 8 Gen 1, ZEISS optics, and 4700mAh battery with fast charging.",
      "Specification": ["Snapdragon 8 Gen 1", "ZEISS Optics", "4700mAh Battery", "80W Fast Charging"],
      "availability": false,
      "rating": 4.5
    },
    {
      "product_id": "P009",
      "product_title": "Oppo Reno8 Pro 5G",
      "product_image": "https://i.ibb.co.com/hmL5bLM/Oppo-Reno8-Pro-5-G-9.jpg",
      "category": "Iphone",
      "price": 599,
      "description": "Oppo Reno8 Pro 5G with MediaTek Dimensity 8100-MAX, 50MP camera, and 4500mAh battery.",
      "Specification": ["MediaTek Dimensity 8100", "50MP Camera", "4500mAh Battery", "80W Fast Charging"],
      "availability": true,
      "rating": 4.4
    },
    {
      "product_id": "P0010",
      "product_title": "Realme GT 2 Pro",
      "product_image": "https://i.ibb.co.com/1JZDW6B/Realme-GT-2-Pro-10.jpg",
      "category": "Smartphones",
      "price": 749,
      "description": "Realme GT 2 Pro with Snapdragon 8 Gen 1, 2K AMOLED display, and stainless steel vapor cooling.",
      "Specification": ["Snapdragon 8 Gen 1", "2K AMOLED", "5000mAh Battery", "65W Fast Charging"],
      "availability": true,
      "rating": 4.6
    },
    {
      "product_id": "P0011",
      "product_title": "Honor Magic4 Pro",
      "product_image": "https://i.ibb.co.com/x2DbC97/Honor-Magic4-Pro-11.jpg",
      "category": "Smartphones",
      "price": 1099,
      "description": "Honor Magic4 Pro with Snapdragon 8 Gen 1, 100W fast wireless charging, and 4600mAh battery.",
      "Specification": ["Snapdragon 8 Gen 1", "100W Wireless Charging", "50MP Triple Camera", "4600mAh Battery"],
      "availability": false,
      "rating": 4.5
    },
    {
      "product_id": "P0012",
      "product_title": "Nokia X30 5G",
      "product_image": "https://i.ibb.co.com/tD5t5Kg/nokia-12.jpg",
      "category": "Smartphones",
      "price": 549,
      "description": "Nokia X30 5G with eco-friendly design, Snapdragon 695, and PureView camera system.",
      "Specification": ["Snapdragon 695", "PureView Camera", "4200mAh Battery", "33W Fast Charging"],
      "availability": true,
      "rating": 4.3
    },
    {
      "product_id": "P0013",
      "product_title": "MacBook pro XPS 15",
      "product_image": "https://i.ibb.co.com/nfWyFXy/omar-al-ghosson-Wrg-25q-Ew-XU-unsplash.jpg",
      "category": "MacBook",
      "price": 179999,
      "description": "MackBook pro  15 with 15.6-inch 4K OLED display, Intel Core i7, and NVIDIA GeForce GTX 1650.",
      "Specification": ["15.6-inch 4K OLED", "Intel Core i7", "16GB RAM", "512GB SSD", "GTX 1650"],
      "availability": true,
      "rating": 4.8,
      "Otherfield": "Color: Platinum Silver"
    },
    {
      "product_id": "P0014",
      "product_title": "MacBook Pro 14-inch",
      "product_image": "https://i.ibb.co.com/qDdhjbB/devon-janse-van-rensburg-z-Uuf57-Um-Yc-unsplash.jpg",
      "category": "MacBook",
      "price": 2499,
      "description": "Apple MacBook Pro with M1 Pro chip, 14.2-inch Liquid Retina XDR display, and 512GB SSD.",
      "Specification": ["M1 Pro Chip", "14.2-inch Liquid Retina", "16GB Unified Memory", "512GB SSD"],
      "availability": true,
      "rating": 4.9,
      "Otherfield": "Battery Life: 17 hours"
    },
    {
      "product_id": "P0015",
      "product_title": "HP Spectre x360 13",
      "product_image": "https://i.ibb.co.com/SRvKHF3/carlos-muza-hpj-Sk-U2-UYSU-unsplash.jpg",
      "category": "Laptops",
      "price": 139999,
      "description": "HP Spectre x360 13 with 13.3-inch FHD touch display, Intel Evo Core i7, and convertible design.",
      "Specification": ["13.3-inch FHD Touch", "Intel Evo Core i7", "16GB RAM", "512GB SSD"],
      "availability": false,
      "rating": 4.6,
      "Otherfield": "Convertible 2-in-1 Design"
    },
    {
      "product_id": "P0016",
      "product_title": "Lenovo ThinkPad X1 Carbon Gen 9",
      "product_image": "https://i.ibb.co.com/yPhD8Lh/anete-lusina-zws-Hjak-E-i-I-unsplash.jpg",
      "category": "Laptops",
      "price": 179900,
      "description": "Lenovo ThinkPad X1 Carbon with 14-inch 4K display, Intel Core i7, and built-in privacy features.",
      "Specification": ["14-inch 4K", "Intel Core i7", "16GB RAM", "1TB SSD", "Privacy Shutter"],
      "availability": true,
      "rating": 4.7,
      "Otherfield": "Security: Fingerprint Reader"
    },
    {
      "product_id": "P0017",
      "product_title": "ASUS ROG Zephyrus G14",
      "product_image": "https://i.ibb.co.com/txj5ZrT/christin-hume-h-Buw-VLc-YTn-A-unsplash.jpg",
      "category": "Laptops",
      "price": 159999,
      "description": "ASUS ROG Zephyrus G14 with AMD Ryzen 9, 14-inch QHD display, and NVIDIA GeForce RTX 3060.",
      "Specification": ["AMD Ryzen 9", "14-inch QHD", "16GB RAM", "1TB SSD", "RTX 3060"],
      "availability": true,
      "rating": 4.8,
      "Otherfield": "Special Feature: Anime Matrix Display"
    },
    {
      "product_id": "P0018",
      "product_title": "Acer Swift 3",
      "product_image": "https://i.ibb.co.com/HNnwzpr/alex-knight-j4uu-Kn-N43-M-unsplash.jpg",
      "category": "Laptops",
      "price": 74999,
      "description": "Acer Swift 3 with 14-inch FHD display, AMD Ryzen 7, lightweight design, and long battery life.",
      "Specification": ["14-inch FHD", "AMD Ryzen 7", "8GB RAM", "512GB SSD"],
      "availability": true,
      "rating": 4.5,
      "Otherfield": "Battery Life: Up to 12 hours"
    },
    {
      "product_id": "P0019",
      "product_title": "Apple Watch Series 8",
      "product_image": "https://i.ibb.co.com/YpNxsh3/david-preston-zhnvtl5x-Qgk-unsplash.jpg",
      "category": "Smartwatches",
      "price": 39900,
      "description": "Apple Watch Series 8 with advanced health tracking, GPS, and water resistance up to 50m.",
      "Specification": ["Health Tracking", "GPS", "50m Water Resistance", "Always-On Retina Display"],
      "availability": true,
      "rating": 4.8
    },
    {
      "product_id": "P0020",
      "product_title": "Samsung Galaxy Watch 5",
      "product_image": "https://example.com/images/galaxy-watch-5.jpg",
      "category": "Smartwatches",
      "price": 27999,
      "description": "Samsung Galaxy Watch 5 with AMOLED display, BioActive sensor, and advanced sleep tracking.",
      "Specification": ["AMOLED Display", "BioActive Sensor", "Sleep Tracking", "Water Resistant"],
      "availability": true,
      "rating": 4.7
    },
    {
      "product_id": "P0021",
      "product_title": "Garmin Forerunner 955",
      "product_image": "https://i.ibb.co.com/XCWvfTn/artur-luczka-NAAkw-Uf0w-S8-unsplash.jpg",
      "category": "Smartwatches",
      "price": 49999,
      "description": "Garmin Forerunner 955 with GPS, heart rate monitoring, and multi-day battery life.",
      "Specification": ["GPS", "Heart Rate Monitoring", "Multi-Day Battery", "VO2 Max Tracking"],
      "availability": true,
      "rating": 4.6
    },
    {
      "product_id": "P0022",
      "product_title": "Fitbit Sense 2",
      "product_image": "https://i.ibb.co.com/GHP7V4r/gijs-coolen-3efw-Rz-EHaoo-unsplash.jpg",
      "category": "Smartwatches",
      "price": 22995,
      "description": "Fitbit Sense 2 with stress management, heart health insights, and sleep tracking.",
      "Specification": ["Stress Management", "Heart Health", "Sleep Tracking", "Water Resistant"],
      "availability": true,
      "rating": 4.5
    },
    {
      "product_id": "P0023",
      "product_title": "Huawei Watch GT 3 Pro",
      "product_image": "https://i.ibb.co.com/Wn2sS3g/artur-luczka-z-Ik-V81-RVw-YY-unsplash.jpg",
      "category": "Smartwatches",
      "price": 34999,
      "description": "Huawei Watch GT 3 Pro with AMOLED display, 14-day battery life, and fitness tracking.",
      "Specification": ["AMOLED Display", "14-Day Battery Life", "Fitness Tracking", "Water Resistant"],
      "availability": false,
      "rating": 4.4
    },
    {
      "product_id": "P0024",
      "product_title": "Amazfit GTR 3",
      "product_image": "https://i.ibb.co.com/vB2RVS4/lloyd-dirks-qd-Y76g-IYbw8-unsplash.jpg",
      "category": "Smartwatches",
      "price": 17999,
      "description": "Amazfit GTR 3 with AMOLED display, GPS, and blood-oxygen monitoring.",
      "Specification": ["AMOLED Display", "GPS", "Blood-Oxygen Monitoring", "Water Resistant"],
      "availability": true,
      "rating": 4.3
    },
    {
    "product_id": "P0025",
    "product_title": "Wireless Bluetooth Headphones",
    "product_image": "https://i.ibb.co.com/xHN4PYB/kiran-ck-RZmi-DOpv1l-M-unsplash.jpg",
    "category": "Accessories",
    "price": 59.99,
    "description": "High-quality wireless Bluetooth headphones with noise cancellation and 20-hour battery life.",
    "Specification": ["Bluetooth 5.0", "Noise Cancellation", "20-hour battery life"],
    "availability": true,
    "rating": 4.5,
    "Otherfield": "Color: Black"
  },
  {
    "product_id": "P0026",
    "product_title": "Pen-drive Ultra Flair 128GB",
    "product_image": "https://i.ibb.co.com/vDTT7sn/arun-prakash-or-DIazr-VPLA-unsplash.jpg",
    "category": "Accessories",
    "price": 1599,
    "description": "SanDisk Ultra Flair USB 3.0 Flash Drive with high-speed transfers up to 150MB/s.",
    "Specification": ["128GB Storage", "USB 3.0", "Up to 150MB/s Transfer Speed", "Metal Casing"],
    "availability": true,
    "rating": 4.7
  },
  {
    "product_id": "P0027",
    "product_title": "Apple Magic Mouse 2",
    "product_image": "https://i.ibb.co.com/vQnzPjP/oscar-ivan-esquivel-arteaga-Ztx-ED1cp-B1-E-unsplash.jpg",
    "category":"Accessories",
    "price": 790,
    "description": "Apple Magic Mouse 2 with multi-touch surface and seamless Apple ecosystem integration.",
    "Specification": ["Multi-Touch Surface", "Bluetooth Connectivity", "Rechargeable Battery", "Minimalist Design"],
    "availability": true,
    "rating": 4.5
  }
    
  ]
  